chunknorris/__init__.py
chunknorris/__main__.py
chunknorris/chunkers/__init__.py
chunknorris/chunkers/abstract_chunker.py
chunknorris/chunkers/markdown_chunker.py
chunknorris/core/__init__.py
chunknorris/core/components.py
chunknorris/core/custom_markdownify.py
chunknorris/core/logger.py
chunknorris/decorators/decorators.py
chunknorris/exceptions/__init__.py
chunknorris/exceptions/exceptions.py
chunknorris/parsers/__init__.py
chunknorris/parsers/abstract_parser.py
chunknorris/parsers/docx/__init__.py
chunknorris/parsers/docx/docx_parser.py
chunknorris/parsers/html/__init__.py
chunknorris/parsers/html/html_parser.py
chunknorris/parsers/json/wikit_parser.py
chunknorris/parsers/markdown/__init__.py
chunknorris/parsers/markdown/markdown_parser.py
chunknorris/parsers/notebook/__init__.py
chunknorris/parsers/notebook/jupyter_notebook_parser.py
chunknorris/parsers/notebook/schemas.py
chunknorris/parsers/pdf/__init__.py
chunknorris/parsers/pdf/pdf_parser.py
chunknorris/parsers/pdf/tools/__init__.py
chunknorris/parsers/pdf/tools/components.py
chunknorris/parsers/pdf/tools/components_tables.py
chunknorris/parsers/pdf/tools/export.py
chunknorris/parsers/pdf/tools/extract_links.py
chunknorris/parsers/pdf/tools/extract_tables.py
chunknorris/parsers/pdf/tools/extract_toc.py
chunknorris/parsers/pdf/tools/plot.py
chunknorris/parsers/pdf/tools/utils.py
chunknorris/parsers/sheets/__init__.py
chunknorris/parsers/sheets/csv_parser.py
chunknorris/parsers/sheets/excel_parser.py
chunknorris/pipelines/__init__.py
chunknorris/pipelines/abstract_pipeline.py
chunknorris/pipelines/base_pipeline.py
chunknorris/pipelines/wikit_pipeline.py
chunknorris/schemas/__init__.py
chunknorris/schemas/schemas.py
chunknorris/types/__init__.py
chunknorris/types/types.py
chunknorris-1.1.9.dist-info/licenses/LICENSE
chunknorris-1.1.9.dist-info/METADATA
chunknorris-1.1.9.dist-info/WHEEL
chunknorris-1.1.9.dist-info/entry_points.txt
chunknorris-1.1.9.dist-info/top_level.txt
chunknorris-1.1.9.dist-info/RECORD
