Metadata-Version: 2.4
Name: chunknorris
Version: 1.1.9
Summary: A package for chunking documents from various formats
Author-email: Wikit <dev@wikit.ai>
Project-URL: Homepage, https://github.com/wikit-ai/chunknorris
Project-URL: Issues, https://github.com/wikit-ai/chunknorris/issues
Project-URL: Documentation, https://wikit-ai.github.io/chunknorris/
Keywords: chunk,document,split,html,markdown,pdf,header,parsing,RAG
Classifier: Natural Language :: English
Classifier: Programming Language :: Python :: 3.11
Classifier: Framework :: Pytest
Classifier: License :: OSI Approved :: GNU Affero General Public License v3
Classifier: Topic :: Text Processing :: Markup :: Markdown
Classifier: Topic :: Text Processing :: Markup :: HTML
Classifier: Operating System :: OS Independent
Requires-Python: >=3.10
License-File: LICENSE
Requires-Dist: markdownify==1.2.0
Requires-Dist: lxml==6.0.2
Requires-Dist: html5lib==1.1
Requires-Dist: termcolor==2.4
Requires-Dist: PyMuPDF==1.25.5
Requires-Dist: matplotlib>=3.9.2
Requires-Dist: pydantic<3.0.0,>=2.0
Requires-Dist: pandas==2.2.3
Requires-Dist: pyyaml==6.0.2
Requires-Dist: openpyxl==3.1.5
Requires-Dist: thefuzz==0.22.1
Requires-Dist: tabulate==0.9.0
Requires-Dist: nbformat==5.10.4
Requires-Dist: mammoth==1.11.0
Provides-Extra: dev
Requires-Dist: pytest==7.4.4; extra == "dev"
Requires-Dist: pytest-cov==4.1.0; extra == "dev"
Requires-Dist: black==24.8.0; extra == "dev"
Requires-Dist: pylint==3.3.1; extra == "dev"
Requires-Dist: mypy; extra == "dev"
Requires-Dist: build; extra == "dev"
Requires-Dist: twine; extra == "dev"
Requires-Dist: mkdocs==1.6.1; extra == "dev"
Requires-Dist: mkdocs-click==0.8.1; extra == "dev"
Requires-Dist: mkdocs-jupyter==0.25.1; extra == "dev"
Requires-Dist: pymdown-extensions==10.12; extra == "dev"
Requires-Dist: mkdocstrings-python==1.12.2; extra == "dev"
Requires-Dist: mkdocs-material==9.5.48; extra == "dev"
Requires-Dist: tiktoken==0.9.0; extra == "dev"
Dynamic: license-file
